secret_duck/__init__.py
secret_duck/__main__.py
secret_duck/secret.py
secret_duck-0.0.4.dist-info/LICENSE
secret_duck-0.0.4.dist-info/METADATA
secret_duck-0.0.4.dist-info/WHEEL
secret_duck-0.0.4.dist-info/entry_points.txt
secret_duck-0.0.4.dist-info/top_level.txt
secret_duck-0.0.4.dist-info/RECORD
