Metadata-Version: 2.1
Name: secret-duck
Version: 0.0.4
Summary: MQTT listener to save data
Author-email: Joe Heffer <j.heffer@sheffield.ac.uk>
Project-URL: Homepage, https://pypi.org/p/secret-duck
Project-URL: Repository, https://github.com/CUREd-Plus/secret-duck
Project-URL: Issues, https://github.com/CUREd-Plus/secret-duck/issues
Project-URL: Changelog, https://github.com/CUREd-Plus/secret-duck/releases
Classifier: Programming Language :: Python :: 3
Classifier: License :: OSI Approved :: MIT License
Classifier: Operating System :: OS Independent
Requires-Python: >=3.9
License-File: LICENSE
Requires-Dist: pykeepass==4.*
Provides-Extra: test
Requires-Dist: pytest; extra == "test"
Requires-Dist: flake8; extra == "test"
Requires-Dist: black; extra == "test"
